byhacker_TTS/__init__.py
byhacker_TTS/tts_selenium.py
byhacker_tts-0.1.0.dist-info/METADATA
byhacker_tts-0.1.0.dist-info/WHEEL
byhacker_tts-0.1.0.dist-info/top_level.txt
byhacker_tts-0.1.0.dist-info/RECORD
