Metadata-Version: 2.4
Name: byhacker_TTS
Version: 0.1.0
Summary: A Selenium-based text-to-speech automation package.
Author: Romil Leuva
Author-email: exmple@gmail.com
License: MIT
Requires-Python: >=3.7
Requires-Dist: selenium
Dynamic: author
Dynamic: author-email
Dynamic: description
Dynamic: description-content-type
Dynamic: license
Dynamic: requires-dist
Dynamic: requires-python
Dynamic: summary
